area_irfankhan/__init__.py
area_irfankhan/library.py
area_irfankhan-0.1.1.dist-info/METADATA
area_irfankhan-0.1.1.dist-info/WHEEL
area_irfankhan-0.1.1.dist-info/top_level.txt
area_irfankhan-0.1.1.dist-info/RECORD
