Metadata-Version: 2.4
Name: area-Irfankhan
Version: 0.1.1
Summary: A simple library to calculate areas of shapes
Author: Irfan Khan
Author-email: irfankhan016104@gmail.com
Dynamic: author
Dynamic: author-email
Dynamic: summary
